<?xml version="1.0" encoding="UTF-8"?>
<products>

 <product>
  <id>I-7</id>
  <name>Bird 7</name>
  <description>Cute bird that loves being in the sun.</description>
  <img-url>images/CIMG9113.jpg</img-url>
  <img-tb-url>images/CIMG9113-s.jpg</img-tb-url>
 </product>
 
 <product>
  <id>I-8</id>
  <name>Bird 8</name>
  <description>This bird likes to sleep.</description>
  <img-url>images/CIMG9102.jpg</img-url>
  <img-tb-url>images/CIMG9102-s.jpg</img-tb-url>
 </product>
 
 <product>
  <id>I-9</id>
  <name>Bird 9</name>
  <description>Cute cat that loves being in the sun..</description>
  <img-url>images/CIMG9162.jpg</img-url>
  <img-tb-url>images/CIMG9162-s.jpg</img-tb-url>
 </product>

 <product>
  <id>I-10</id>
  <name>Bird 10</name>
  <description>Cute cat that loves being in the sun.</description>
  <img-url>images/CIMG9105.jpg</img-url>
  <img-tb-url>images/CIMG9115-s.jpg</img-tb-url>
 </product>

 <product>
  <id>I-11</id>
  <name>Bird 11</name>
  <description>This cat thinks she is a princess.</description>
  <img-url>images/CIMG9104.jpg</img-url>
  <img-tb-url>images/CIMG9104-s.jpg</img-tb-url>
 </product>
 
 <product>
  <id>I-12</id>
  <name>Bird 12</name>
  <description>Cute cat that loves being in the sun.</description>
  <img-url>images/CIMG9107.jpg</img-url>
  <img-tb-url>images/CIMG9107-s.jpg</img-tb-url>
 </product>
 
 <product>
  <id>I-13</id>
  <name>Bird 13</name>
  <description>Cute cat that loves being in the sun.</description>
  <img-url>images/CIMG9109.jpg</img-url>
  <img-tb-url>images/CIMG9109-s.jpg</img-tb-url>
 </product>

</products>